swevolml/GML.py
swevolml/__init__.py
swevolml/graphtest.py
SWEvolML-0.1.0.dist-info/METADATA
SWEvolML-0.1.0.dist-info/WHEEL
SWEvolML-0.1.0.dist-info/entry_points.txt
SWEvolML-0.1.0.dist-info/top_level.txt
SWEvolML-0.1.0.dist-info/RECORD
