Metadata-Version: 2.1
Name: SWEvolML
Version: 0.1.0
Summary: Default template for PDM package
Author-email: GITSangWoo <dogcenta@gmail.com>
License: MIT
Project-URL: Homepage, https://github.com/GITSangWoo/SWEvolML
Project-URL: Issues, https://github.com/GITSangWoo/SWEvolML/issues
Requires-Python: ==3.11.*
Requires-Dist: pandas>=2.2.2
Requires-Dist: scikit-learn>=1.5.1
Requires-Dist: plotext>=5.2.8
